django_codemirror6/__init__.py
django_codemirror6/admin.py
django_codemirror6/apps.py
django_codemirror6/models.py
django_codemirror6/tests.py
django_codemirror6/urls.py
django_codemirror6/views.py
django_codemirror6/migrations/__init__.py
django_codemirror6/static/cm6/cm6-all-yjs.js
django_codemirror6/static/cm6/cm6-all-yjs.min.js
django_codemirror6/static/cm6/cm6-all.js
django_codemirror6/static/cm6/cm6-all.min.js
django_codemirror6/static/cm6/cm6-cpp-yjs.js
django_codemirror6/static/cm6/cm6-cpp-yjs.min.js
django_codemirror6/static/cm6/cm6-cpp.js
django_codemirror6/static/cm6/cm6-cpp.min.js
django_codemirror6/static/cm6/cm6-css-yjs.js
django_codemirror6/static/cm6/cm6-css-yjs.min.js
django_codemirror6/static/cm6/cm6-css.js
django_codemirror6/static/cm6/cm6-css.min.js
django_codemirror6/static/cm6/cm6-html-yjs.js
django_codemirror6/static/cm6/cm6-html-yjs.min.js
django_codemirror6/static/cm6/cm6-html.js
django_codemirror6/static/cm6/cm6-html.min.js
django_codemirror6/static/cm6/cm6-java-yjs.js
django_codemirror6/static/cm6/cm6-java-yjs.min.js
django_codemirror6/static/cm6/cm6-java.js
django_codemirror6/static/cm6/cm6-java.min.js
django_codemirror6/static/cm6/cm6-javascript-yjs.js
django_codemirror6/static/cm6/cm6-javascript-yjs.min.js
django_codemirror6/static/cm6/cm6-javascript.js
django_codemirror6/static/cm6/cm6-javascript.min.js
django_codemirror6/static/cm6/cm6-json-yjs.js
django_codemirror6/static/cm6/cm6-json-yjs.min.js
django_codemirror6/static/cm6/cm6-json.js
django_codemirror6/static/cm6/cm6-json.min.js
django_codemirror6/static/cm6/cm6-markdown-yjs.js
django_codemirror6/static/cm6/cm6-markdown-yjs.min.js
django_codemirror6/static/cm6/cm6-markdown.js
django_codemirror6/static/cm6/cm6-markdown.min.js
django_codemirror6/static/cm6/cm6-php-yjs.js
django_codemirror6/static/cm6/cm6-php-yjs.min.js
django_codemirror6/static/cm6/cm6-php.js
django_codemirror6/static/cm6/cm6-php.min.js
django_codemirror6/static/cm6/cm6-python-yjs.js
django_codemirror6-1.0.1.dist-info/LICENSE
django_codemirror6-1.0.1.dist-info/METADATA
django_codemirror6-1.0.1.dist-info/WHEEL
django_codemirror6-1.0.1.dist-info/top_level.txt
django_codemirror6-1.0.1.dist-info/RECORD
