Metadata-Version: 2.1
Name: django-codemirror6
Version: 1.0.1
Summary: Django CodeMirror 6
Author-email: Grant Jenks <contact@grantjenks.com>
License: Apache 2.0
Project-URL: Documentation, https://grantjenks.com/docs/django-codemirror6/
Project-URL: Source, https://github.com/grantjenks/django-codemirror6
Project-URL: Tracker, https://github.com/grantjenks/django-codemirror6/issues
Keywords: django,codemirror
Classifier: Development Status :: 5 - Production/Stable
Classifier: Framework :: Django
Classifier: Intended Audience :: Developers
Classifier: License :: OSI Approved :: Apache Software License
Classifier: Natural Language :: English
Classifier: Programming Language :: Python
Classifier: Programming Language :: Python :: 3
Requires-Python: >=3.7
License-File: LICENSE
Requires-Dist: Django
